{
    "file_path": "/content/drive/MyDrive/Colab Notebooks/day17_pics/Screenshot 2026-01-08 192545.png",
    "description": {
        "main_subject": "Pixel art forest path",
        "detailed_description": "A vibrant pixel art image depicts a winding dirt path through a dense, lush green forest. Footprints are visible along the path, suggesting recent travel, while a wooden sign is partially seen on the left. The scene is brightly lit, conveying a tranquil and inviting atmosphere for exploration.",
        "visual_elements": [
            "Pixel art",
            "Forest",
            "Trees",
            "Green foliage",
            "Dirt path",
            "Footprints",
            "Wooden sign",
            "Partial character (hair)",
            "Leaves",
            "Grass"
        ],
        "text_content": "st",
        "search_keywords": [
            "pixel art",
            "forest path",
            "woodland",
            "nature",
            "adventure",
            "RPG",
            "game art",
            "footprints",
            "green trees",
            "dirt trail",
            "signpost",
            "outdoor",
            "fantasy",
            "exploration",
            "tranquil"
        ]
    }
}